{
  "updated_at": "2026-06-08T16:17:44Z",
  "source_name": "lotto-italia.it",
  "source_url": "https://www.lotto-italia.it/millionday/estratti",
  "is_demo": false,
  "draw": {
    "draw_id": "2026-06-08-midday",
    "date": "2026-06-08",
    "slot": "midday",
    "time": "13:00",
    "numbers": [
      2,
      11,
      32,
      35,
      42
    ],
    "numbers_sorted": [
      2,
      11,
      32,
      35,
      42
    ],
    "extra_numbers": [
      8,
      16,
      26,
      37,
      55
    ],
    "extra_numbers_sorted": [
      8,
      16,
      26,
      37,
      55
    ],
    "source": "lotto-italia.it",
    "source_url": "https://www.lotto-italia.it/millionday/estratti"
  }
}
